{
  "unit": 651,
  "companyCode": "NO",
  "companyName": "Confirmit",
  "project": "Studio",
  "employees": [
    {
      "name": "Kachalov Alexey",
      "jiraUsername": "alexeyk",
      "position": "TeamLead"
    },
    {
      "name": "Kolokolenkina Natalia",
      "jiraUsername": "NataliaK",
      "position": "SoftwareEngineer"
    },
    {
      "name": "Kozlova Anna",
      "jiraUsername": "AnnaKo",
      "position": "SoftwareEngineer"
    },
    {
      "name": "Pisarenko Dmitry",
      "jiraUsername": "DmitryP",
      "position": "SoftwareEngineer"
    },
    {
      "name": "Popov Sergey",
      "jiraUsername": "SergeyPo",
      "position": "SoftwareEngineer"
    },
    {
      "name": "Protasov Ilya",
      "jiraUsername": "Ilia.Protasov",
      "position": "SoftwareEngineer"
    },
    {
      "name": "Sumatokhin Alexey",
      "jiraUsername": "AlexeySu",
      "position": "SoftwareEngineer"
    },
    {
      "name": "Volyakov Dmitry",
      "jiraUsername": "DmitryV",
      "position": "SoftwareEngineer"
    },
    {
      "name": "Volyakova Kristina",
      "jiraUsername": "KristinaZ",
      "position": "SoftwareEngineer"
    }
  ]
}